aion/__init__.py
aion/modalities.py
aion/model.py
aion/codecs/__init__.py
aion/codecs/base.py
aion/codecs/catalog.py
aion/codecs/config.py
aion/codecs/image.py
aion/codecs/manager.py
aion/codecs/scalar.py
aion/codecs/scalar_field.py
aion/codecs/spectrum.py
aion/codecs/utils.py
aion/codecs/modules/__init__.py
aion/codecs/modules/convblocks.py
aion/codecs/modules/convnext.py
aion/codecs/modules/ema.py
aion/codecs/modules/magvit.py
aion/codecs/modules/spectrum.py
aion/codecs/modules/subsampler.py
aion/codecs/modules/utils.py
aion/codecs/preprocessing/band_to_index.py
aion/codecs/preprocessing/image.py
aion/codecs/quantizers/__init__.py
aion/codecs/quantizers/lookup_free_quantization.py
aion/codecs/quantizers/scalar.py
aion/fourm/__init__.py
aion/fourm/decoder_embeddings.py
aion/fourm/encoder_embeddings.py
aion/fourm/fm.py
aion/fourm/fm_utils.py
aion/fourm/generate.py
aion/fourm/generation_utils.py
aion/fourm/lora_utils.py
aion/fourm/modality_info.py
aion/fourm/modality_transforms.py
aion/fourm/text_utils.py
polymathic_aion-0.0.2.dist-info/licenses/LICENSE
polymathic_aion-0.0.2.dist-info/METADATA
polymathic_aion-0.0.2.dist-info/WHEEL
polymathic_aion-0.0.2.dist-info/top_level.txt
polymathic_aion-0.0.2.dist-info/RECORD
