Metadata-Version: 2.4
Name: polymathic-aion
Version: 0.0.2
Summary: AstronomIcal Omnimodal Network - Polymathic's Large Omnimodal Model for Astronomy
Author-email: Polymathic AI <info@polymathic-ai.org>
Maintainer-email: Polymathic AI <info@polymathic-ai.org>
License: MIT
Project-URL: Homepage, https://polymathic-ai.org/
Project-URL: Documentation, https://polymathic-ai.github.io/AION/
Project-URL: Repository, https://github.com/PolymathicAI/AION
Project-URL: Bug Tracker, https://github.com/PolymathicAI/AION/issues
Project-URL: Discussion, https://github.com/PolymathicAI/AION/discussions
Project-URL: Hugging Face, https://huggingface.co/polymathic-ai/aion-base
Keywords: astronomy,astrophysics,machine learning,transformer,multimodal,deep learning,scientific computing,AI
Classifier: Development Status :: 4 - Beta
Classifier: Intended Audience :: Science/Research
Classifier: License :: OSI Approved :: MIT License
Classifier: Operating System :: OS Independent
Classifier: Programming Language :: Python :: 3
Classifier: Programming Language :: Python :: 3.10
Classifier: Programming Language :: Python :: 3.11
Classifier: Programming Language :: Python :: 3.12
Classifier: Topic :: Scientific/Engineering :: Astronomy
Classifier: Topic :: Scientific/Engineering :: Artificial Intelligence
Classifier: Topic :: Scientific/Engineering :: Physics
Requires-Python: >=3.10
License-File: LICENSE
Requires-Dist: einops>=0.7.0
Requires-Dist: huggingface_hub>=0.24.7
Requires-Dist: jaxtyping>=0.2.28
Requires-Dist: numpy
Requires-Dist: scipy
Requires-Dist: tokenizers>=0.15.2
Provides-Extra: torch
Requires-Dist: torch>=2.4.0; extra == "torch"
Requires-Dist: huggingface_hub[torch]>=0.24.7; extra == "torch"
Provides-Extra: dev
Requires-Dist: pre-commit; extra == "dev"
Requires-Dist: pytest; extra == "dev"
Requires-Dist: ruff; extra == "dev"
Provides-Extra: docs
Requires-Dist: furo; extra == "docs"
Requires-Dist: myst-parser>=1.0; extra == "docs"
Requires-Dist: sphinx-copybutton; extra == "docs"
Requires-Dist: sphinx-design; extra == "docs"
Requires-Dist: sphinxcontrib-mermaid; extra == "docs"
Requires-Dist: sphinx>=7.2; extra == "docs"
Dynamic: license-file
